{
  "animateLoading": true,
  "borderRadius": "{{appsmith.theme.borderRadius.appBorderRadius}}",
  "bottomRow": 8,
  "dynamicBindingPathList": [
    {
      "key": "truncateButtonColor"
    },
    {
      "key": "fontFamily"
    },
    {
      "key": "borderRadius"
    },
    {
      "key": "text"
    }
  ],
  "dynamicHeight": "AUTO_HEIGHT",
  "dynamicTriggerPathList": [],
  "fontFamily": "{{appsmith.theme.fontFamily.appFont}}",
  "fontSize": "1rem",
  "fontStyle": "",
  "isLoading": false,
  "isVisible": true,
  "key": "tfr6ttqb0e",
  "leftColumn": 28,
  "maxDynamicHeight": 9000,
  "minDynamicHeight": 4,
  "minWidth": 450,
  "mobileBottomRow": 6,
  "mobileLeftColumn": 28,
  "mobileRightColumn": 44,
  "mobileTopRow": 2,
  "needsErrorInfo": false,
  "overflow": "NONE",
  "parentColumnSpace": 19.62109375,
  "parentId": "vd87qdaouw",
  "parentRowSpace": 10,
  "renderMode": "CANVAS",
  "responsiveBehavior": "fill",
  "rightColumn": 44,
  "shouldTruncate": false,
  "text": "{{\n  \"Monto Total: $ \" +\n  (\n    (Query_CxP_Resumen.data || [])\n      .reduce((acc, row) => acc + (row.monto_total || 0), 0)\n      .toLocaleString(\"en-US\", { minimumFractionDigits: 2 })\n  )\n}}",
  "textAlign": "LEFT",
  "textColor": "#231F20",
  "topRow": 4,
  "truncateButtonColor": "{{appsmith.theme.colors.primaryColor}}",
  "type": "TEXT_WIDGET",
  "version": 1,
  "widgetId": "xe8hvv2rje",
  "widgetName": "Monto_Total_Resumen"
}