{
  "accentColor": "{{appsmith.theme.colors.primaryColor}}",
  "animateLoading": true,
  "borderRadius": "{{appsmith.theme.borderRadius.appBorderRadius}}",
  "bottomRow": 7,
  "boxShadow": "none",
  "defaultOptionValue": "",
  "dynamicBindingPathList": [
    {
      "key": "accentColor"
    },
    {
      "key": "borderRadius"
    },
    {
      "key": "sourceData"
    }
  ],
  "dynamicHeight": "FIXED",
  "dynamicPropertyPathList": [
    {
      "key": "sourceData"
    }
  ],
  "dynamicTriggerPathList": [],
  "isDisabled": false,
  "isFilterable": true,
  "isLoading": false,
  "isRequired": false,
  "isVisible": true,
  "key": "kzrmlzvw3m",
  "labelAlignment": "left",
  "labelPosition": "Top",
  "labelText": "Seleccione un suplidor",
  "labelTextSize": "0.875rem",
  "labelWidth": 5,
  "leftColumn": 1,
  "maxDynamicHeight": 9000,
  "minDynamicHeight": 4,
  "minWidth": 450,
  "mobileBottomRow": 15,
  "mobileLeftColumn": 1,
  "mobileRightColumn": 21,
  "mobileTopRow": 8,
  "needsErrorInfo": false,
  "optionLabel": "razon_social",
  "optionValue": "id_suplidor",
  "parentColumnSpace": 19.3046875,
  "parentId": "k28n3zmeto",
  "parentRowSpace": 10,
  "placeholderText": "Select option",
  "renderMode": "CANVAS",
  "responsiveBehavior": "fill",
  "rightColumn": 21,
  "serverSideFiltering": false,
  "sourceData": "{{ Query_Suplidores_Av.data }}",
  "topRow": 0,
  "type": "SELECT_WIDGET",
  "version": 1,
  "widgetId": "utudun2pt4",
  "widgetName": "DD_Suplidor_Av"
}